self_supervised/__init__.py
self_supervised/_nbdev.py
self_supervised/augmentations.py
self_supervised/dist.py
self_supervised/layers.py
self_supervised/models/__init__.py
self_supervised/models/vision_transformer.py
self_supervised/multimodal/__init__.py
self_supervised/multimodal/clip.py
self_supervised/multimodal/clip_moco.py
self_supervised/vision/__init__.py
self_supervised/vision/barlow_twins.py
self_supervised/vision/byol.py
self_supervised/vision/dino.py
self_supervised/vision/metrics.py
self_supervised/vision/moco.py
self_supervised/vision/simclr.py
self_supervised/vision/swav.py
self_supervised-1.0.4.dist-info/LICENSE
self_supervised-1.0.4.dist-info/METADATA
self_supervised-1.0.4.dist-info/WHEEL
self_supervised-1.0.4.dist-info/entry_points.txt
self_supervised-1.0.4.dist-info/top_level.txt
self_supervised-1.0.4.dist-info/RECORD
