Metadata-Version: 2.1
Name: self-supervised
Version: 1.0.4
Summary: Self Supervised Learning Algorithms with Fastai
Home-page: https://github.com/keremturgutlu/self_supervised/tree/main/
Author: Kerem Turgutlu
Author-email: keremturgutlu@gmail.com
License: Apache Software License 2.0
Keywords: self supervised learning,feature learning,deep learning,fastai
Platform: UNKNOWN
Classifier: Development Status :: 3 - Alpha
Classifier: Intended Audience :: Developers
Classifier: License :: OSI Approved :: Apache Software License
Classifier: Natural Language :: English
Classifier: Programming Language :: Python :: 3.6
Classifier: Programming Language :: Python :: 3.7
Classifier: Programming Language :: Python :: 3.8
Requires-Python: >=3.6
Requires-Dist: pip
Requires-Dist: packaging
Requires-Dist: fastai (>=2.2.7)
Requires-Dist: kornia (>=0.5.0)
Requires-Dist: timm (>=0.4.5)
Provides-Extra: dev
Requires-Dist: nbdev (>=1.0.10) ; extra == 'dev'
Requires-Dist: ftfy ; extra == 'dev'
Requires-Dist: regex ; extra == 'dev'
Requires-Dist: tqdm ; extra == 'dev'
